jupyter_remote_runner/__init__.py
jupyter_remote_runner/__main__.py
jupyter_remote_runner/cli.py
jupyter_remote_runner/daemon.py
jupyter_remote_runner/kernel.py
jupyter_remote_runner-0.1.1.dist-info/entry_points.txt
jupyter_remote_runner-0.1.1.dist-info/METADATA
jupyter_remote_runner-0.1.1.dist-info/WHEEL
jupyter_remote_runner-0.1.1.dist-info/RECORD
