Metadata-Version: 2.3
Name: jupyter-remote-runner
Version: 0.1.1
Summary: CLI interface to a persistent Jupyter kernel for code execution with timeout handling
Author: User
Author-email: user@example.com
Requires-Python: >=3.8,<4.0
Classifier: Development Status :: 3 - Alpha
Classifier: Intended Audience :: Developers
Classifier: License :: OSI Approved :: MIT License
Classifier: Programming Language :: Python :: 3
Classifier: Programming Language :: Python :: 3.8
Classifier: Programming Language :: Python :: 3.9
Classifier: Programming Language :: Python :: 3.10
Classifier: Programming Language :: Python :: 3.11
Classifier: Programming Language :: Python :: 3.12
Classifier: Programming Language :: Python :: 3.13
Requires-Dist: click (>=8.0.0,<9.0.0)
Requires-Dist: jupyter-client (>=7.0.0,<8.0.0)
Requires-Dist: platformdirs (>=3.0.0,<4.0.0)
Project-URL: Homepage, https://github.com/user/jupyter-remote-runner
Project-URL: Repository, https://github.com/user/jupyter-remote-runner
